formtool/__init__.py
formtool/__main__.py
formtool-1.0.0.dist-info/METADATA
formtool-1.0.0.dist-info/WHEEL
formtool-1.0.0.dist-info/entry_points.txt
formtool-1.0.0.dist-info/top_level.txt
formtool-1.0.0.dist-info/RECORD
