Metadata-Version: 2.4
Name: formtool
Version: 1.0.0
Summary: ffmpeg command shortcuts
Requires-Python: >=3.10
Requires-Dist: hypy-utils>=1.0.29
Requires-Dist: rich>=14.1.0
